<?xml version="1.0" encoding="UTF-8"?><record_update table="sys_ws_definition">
    <sys_ws_definition action="DELETE">
        <active>true</active>
        <base_uri>/api/x_boalh_hloder/hlodr_rest_scripted</base_uri>
        <consumes>application/json,application/xml,text/xml</consumes>
        <consumes_customized>false</consumes_customized>
        <default_version>No active default version</default_version>
        <doc_link/>
        <enforce_acl>cf9d01d3e73003009d6247e603f6a990</enforce_acl>
        <is_versioned>false</is_versioned>
        <name>HLODR REST - Scripted</name>
        <namespace>x_boalh_hloder</namespace>
        <produces>application/json,application/xml,text/xml</produces>
        <produces_customized>false</produces_customized>
        <service_id>hlodr_rest_scripted</service_id>
        <short_description/>
        <sys_class_name>sys_ws_definition</sys_class_name>
        <sys_created_by>Tim.Abiok</sys_created_by>
        <sys_created_on>2021-01-31 03:26:55</sys_created_on>
        <sys_id>81766b551b4a6c10c34ca8672a4bcb12</sys_id>
        <sys_mod_count>0</sys_mod_count>
        <sys_name>HLODR REST - Scripted</sys_name>
        <sys_package display_value="HLODR" source="x_boalh_hloder">192583c9dbf964104540240a139619f6</sys_package>
        <sys_policy>protected</sys_policy>
        <sys_scope display_value="HLODR">192583c9dbf964104540240a139619f6</sys_scope>
        <sys_update_name>sys_ws_definition_81766b551b4a6c10c34ca8672a4bcb12</sys_update_name>
        <sys_updated_by>Tim.Abiok</sys_updated_by>
        <sys_updated_on>2021-01-31 03:26:55</sys_updated_on>
    </sys_ws_definition>
    <sys_update_version action="INSERT_OR_UPDATE">
        <action>DELETE</action>
        <application display_value="HLODR">192583c9dbf964104540240a139619f6</application>
        <file_path/>
        <instance_id>a4d24a89db3cff800ae3ac44d4961957</instance_id>
        <instance_name>boozallendemo6</instance_name>
        <name>sys_ws_definition_81766b551b4a6c10c34ca8672a4bcb12</name>
        <payload><![CDATA[<?xml version="1.0" encoding="UTF-8"?><record_update table="sys_ws_definition"><sys_ws_definition action="INSERT_OR_UPDATE"><active>true</active><base_uri>/api/x_boalh_hloder/hlodr_rest_scripted</base_uri><consumes>application/json,application/xml,text/xml</consumes><consumes_customized>false</consumes_customized><default_version>No active default version</default_version><doc_link/><enforce_acl>cf9d01d3e73003009d6247e603f6a990</enforce_acl><is_versioned>false</is_versioned><name>HLODR REST - Scripted</name><namespace>x_boalh_hloder</namespace><produces>application/json,application/xml,text/xml</produces><produces_customized>false</produces_customized><service_id>hlodr_rest_scripted</service_id><short_description/><sys_class_name>sys_ws_definition</sys_class_name><sys_created_by>Tim.Abiok</sys_created_by><sys_created_on>2021-01-31 03:26:55</sys_created_on><sys_id>81766b551b4a6c10c34ca8672a4bcb12</sys_id><sys_mod_count>0</sys_mod_count><sys_name>HLODR REST - Scripted</sys_name><sys_package display_value="HLODR" source="x_boalh_hloder">192583c9dbf964104540240a139619f6</sys_package><sys_policy>protected</sys_policy><sys_scope display_value="HLODR">192583c9dbf964104540240a139619f6</sys_scope><sys_update_name>sys_ws_definition_81766b551b4a6c10c34ca8672a4bcb12</sys_update_name><sys_updated_by>Tim.Abiok</sys_updated_by><sys_updated_on>2021-01-31 03:26:55</sys_updated_on></sys_ws_definition></record_update>]]></payload>
        <payload_hash>974279174</payload_hash>
        <record_name>HLODR REST - Scripted</record_name>
        <reverted_from/>
        <source>992583c9dbf964104540240a139619f8</source>
        <source_table>sys_update_set</source_table>
        <state>previous</state>
        <sys_created_by>Tim.Abiok</sys_created_by>
        <sys_created_on>2021-01-31 03:26:55</sys_created_on>
        <sys_id>00c66b551b4a6c10c34ca8672a4bcb20</sys_id>
        <sys_mod_count>0</sys_mod_count>
        <sys_recorded_at>177567aaa070000001</sys_recorded_at>
        <sys_updated_by>Tim.Abiok</sys_updated_by>
        <sys_updated_on>2021-01-31 03:26:55</sys_updated_on>
        <type>Scripted REST API</type>
        <update_guid>08c66b55704a6c1069fc9a4c2e21f91f</update_guid>
        <update_guid_history>08c66b55704a6c1069fc9a4c2e21f91f:974279174</update_guid_history>
    </sys_update_version>
    <sys_metadata_delete action="INSERT_OR_UPDATE">
        <sys_audit_delete/>
        <sys_class_name>sys_metadata_delete</sys_class_name>
        <sys_created_by>Tim.Abiok</sys_created_by>
        <sys_created_on>2021-01-31 03:33:17</sys_created_on>
        <sys_db_object display_value="" name="sys_ws_definition">sys_ws_definition</sys_db_object>
        <sys_id>218fde04b615412b9e91a888773e7a81</sys_id>
        <sys_metadata>81766b551b4a6c10c34ca8672a4bcb12</sys_metadata>
        <sys_mod_count>0</sys_mod_count>
        <sys_name>HLODR REST - Scripted</sys_name>
        <sys_package display_value="HLODR" source="x_boalh_hloder">192583c9dbf964104540240a139619f6</sys_package>
        <sys_parent/>
        <sys_policy>protected</sys_policy>
        <sys_scope display_value="HLODR">192583c9dbf964104540240a139619f6</sys_scope>
        <sys_scope_delete display_value="">1aec6ce10d9b4fb4a6338e60928f4271</sys_scope_delete>
        <sys_update_name>sys_ws_definition_81766b551b4a6c10c34ca8672a4bcb12</sys_update_name>
        <sys_update_version display_value="sys_ws_definition_81766b551b4a6c10c34ca8672a4bcb12">00c66b551b4a6c10c34ca8672a4bcb20</sys_update_version>
        <sys_updated_by>Tim.Abiok</sys_updated_by>
        <sys_updated_on>2021-01-31 03:33:17</sys_updated_on>
    </sys_metadata_delete>
</record_update>
